wcpy/__init__.py
wcpy/core.py
wcpy/io.py
wcpy/script.py
wcpy/ui/__init__.py
wcpy/ui/fonts.py
wcpy/ui/mainwindow.py
wcpy/ui/widgets.py
astro_wcpy-0.0.2.1.dist-info/LICENSE
astro_wcpy-0.0.2.1.dist-info/METADATA
astro_wcpy-0.0.2.1.dist-info/WHEEL
astro_wcpy-0.0.2.1.dist-info/entry_points.txt
astro_wcpy-0.0.2.1.dist-info/top_level.txt
astro_wcpy-0.0.2.1.dist-info/RECORD
